mantis/__init__.py
mantis/cli.py
mantis/extract.py
mantis/models.py
mantis/summarize.py
mantis/transcription.py
mantis/utils.py
mantisai-0.1.18.dist-info/METADATA
mantisai-0.1.18.dist-info/WHEEL
mantisai-0.1.18.dist-info/entry_points.txt
mantisai-0.1.18.dist-info/licenses/LICENSE
mantisai-0.1.18.dist-info/RECORD
