Metadata-Version: 2.4
Name: mantisai
Version: 0.1.18
Summary: A Python package for transcribing audio files, summarizing text, and extracting information using Gemini AI and Pydantic.
Author-email: Paul Elliot <paul@paulelliot.co>
License: Apache 2.0
License-File: LICENSE
Classifier: License :: OSI Approved :: Apache Software License
Classifier: Operating System :: OS Independent
Classifier: Programming Language :: Python :: 3
Classifier: Programming Language :: Python :: 3.9
Classifier: Programming Language :: Python :: 3.10
Classifier: Programming Language :: Python :: 3.11
Classifier: Programming Language :: Python :: 3.12
Requires-Python: <4.0,>=3.9
Requires-Dist: google-generativeai<0.9.0,>=0.8.0
Requires-Dist: grpcio==1.60.1
Requires-Dist: pydantic<3.0.0,>=2.0.0
Requires-Dist: python-dotenv<2.0.0,>=1.0.0
Requires-Dist: requests<3.0.0,>=2.28.0
Requires-Dist: rich<14.0.0,>=13.0.0
Requires-Dist: tenacity<9.0.0,>=8.0.0
Requires-Dist: yt-dlp>=2023.10.0
Provides-Extra: dev
Requires-Dist: black<24.0.0,>=23.0.0; extra == 'dev'
Requires-Dist: flake8<7.0.0,>=6.0.0; extra == 'dev'
Requires-Dist: pytest-cov<5.0.0,>=4.0.0; extra == 'dev'
Requires-Dist: pytest<8.0.0,>=7.0.0; extra == 'dev'
Requires-Dist: speechrecognition<4.0.0,>=3.0.0; extra == 'dev'
Requires-Dist: sphinx-autodoc-typehints<2.0.0,>=1.0.0; extra == 'dev'
Requires-Dist: sphinx-rtd-theme<2.0.0,>=1.0.0; extra == 'dev'
Requires-Dist: sphinx<8.0.0,>=7.0.0; extra == 'dev'
